my_package/__init__.py
my_package/core.py
persistency/__init__.py
persistency/cli.py
persistency/fit.py
persistency/forecast.py
persistency/io.py
persistency/model.py
persistency/report.py
vbz_drug_persistency-0.1.3.dist-info/licenses/LICENSE
vbz_drug_persistency-0.1.3.dist-info/METADATA
vbz_drug_persistency-0.1.3.dist-info/WHEEL
vbz_drug_persistency-0.1.3.dist-info/entry_points.txt
vbz_drug_persistency-0.1.3.dist-info/top_level.txt
vbz_drug_persistency-0.1.3.dist-info/RECORD
