Metadata-Version: 2.4
Name: vbz-drug-persistency
Version: 0.1.3
Summary: Retention-based TRx projection using NBRx and VBZ S(t)
Author-email: Santhosh Kumar Ramaraj <santhu.hi@gmail.com>
License: MIT
Keywords: healthcare,forecasting,retention,weibull,prescriptions
Classifier: Programming Language :: Python :: 3
Classifier: License :: OSI Approved :: MIT License
Requires-Python: >=3.9
License-File: LICENSE
Requires-Dist: pandas>=2.0
Requires-Dist: openpyxl>=3.1
Requires-Dist: scipy>=1.10
Dynamic: license-file
